{"Layers":[{"LayerType":{"$type":"Artemis.Profiles.Layers.Types.Keyboard.KeyboardType, Artemis"},"LayerCondition":{"$type":"Artemis.Profiles.Layers.Conditions.DataModelCondition, Artemis"},"LayerAnimation":{"$type":"Artemis.Profiles.Layers.Animations.NoneAnimation, Artemis"},"Name":"0","Order":0,"Enabled":true,"RenderAllowed":true,"Expanded":false,"IsEvent":false,"Properties":{"$type":"Artemis.Profiles.Layers.Types.Keyboard.KeyboardPropertiesModel, Artemis","GifFile":null,"X":10.0,"Y":1.0,"Width":1.0,"Height":1.0,"Contain":false,"Opacity":1.0,"AnimationSpeed":0.0,"OpacityEaseTime":0.0,"HeightEaseTime":0.0,"WidthEaseTime":0.0,"WidthEase":"Linear","HeightEase":"Linear","OpacityEase":"Linear","ConditionType":1,"Conditions":[{"Field":"CurrentTime.Seconds","Value":"0","Operator":"==","Type":"Int32","HotKey":null},{"Field":"CurrentTime.Seconds","Value":"10","Operator":"==","Type":"Int32","HotKey":null},{"Field":"CurrentTime.Seconds","Value":"20","Operator":"==","Type":"Int32","HotKey":null},{"Field":"CurrentTime.Seconds","Value":"30","Operator":"==","Type":"Int32","HotKey":null},{"Field":"CurrentTime.Seconds","Value":"40","Operator":"==","Type":"Int32","HotKey":null},{"Field":"CurrentTime.Seconds","Value":"50","Operator":"==","Type":"Int32","HotKey":null}],"LayerKeybindModels":[],"DynamicProperties":[],"Brush":{"SolidColorBrush":{"@xmlns":"http://schemas.microsoft.com/winfx/2006/xaml/presentation","#text":"#FF8000FF"}}},"EventProperties":null,"Children":[]},{"LayerType":{"$type":"Artemis.Profiles.Layers.Types.Keyboard.KeyboardType, Artemis"},"LayerCondition":{"$type":"Artemis.Profiles.Layers.Conditions.DataModelCondition, Artemis"},"LayerAnimation":{"$type":"Artemis.Profiles.Layers.Animations.NoneAnimation, Artemis"},"Name":"1","Order":1,"Enabled":true,"RenderAllowed":true,"Expanded":false,"IsEvent":false,"Properties":{"$type":"Artemis.Profiles.Layers.Types.Keyboard.KeyboardPropertiesModel, Artemis","GifFile":null,"X":1.0,"Y":1.0,"Width":1.0,"Height":1.0,"Contain":false,"Opacity":1.0,"AnimationSpeed":0.0,"OpacityEaseTime":0.0,"HeightEaseTime":0.0,"WidthEaseTime":0.0,"WidthEase":"Linear","HeightEase":"Linear","OpacityEase":"Linear","ConditionType":1,"Conditions":[{"Field":"CurrentTime.Seconds","Value":"1","Operator":"==","Type":"Int32","HotKey":null},{"Field":"CurrentTime.Seconds","Value":"11","Operator":"==","Type":"Int32","HotKey":null},{"Field":"CurrentTime.Seconds","Value":"21","Operator":"==","Type":"Int32","HotKey":null},{"Field":"CurrentTime.Seconds","Value":"31","Operator":"==","Type":"Int32","HotKey":null},{"Field":"CurrentTime.Seconds","Value":"41","Operator":"==","Type":"Int32","HotKey":null},{"Field":"CurrentTime.Seconds","Value":"51","Operator":"==","Type":"Int32","HotKey":null}],"LayerKeybindModels":[],"DynamicProperties":[],"Brush":{"SolidColorBrush":{"@xmlns":"http://schemas.microsoft.com/winfx/2006/xaml/presentation","#text":"#FF8000FF"}}},"EventProperties":null,"Children":[]},{"LayerType":{"$type":"Artemis.Profiles.Layers.Types.Keyboard.KeyboardType, Artemis"},"LayerCondition":{"$type":"Artemis.Profiles.Layers.Conditions.DataModelCondition, Artemis"},"LayerAnimation":{"$type":"Artemis.Profiles.Layers.Animations.NoneAnimation, Artemis"},"Name":"2","Order":2,"Enabled":true,"RenderAllowed":true,"Expanded":true,"IsEvent":false,"Properties":{"$type":"Artemis.Profiles.Layers.Types.Keyboard.KeyboardPropertiesModel, Artemis","GifFile":null,"X":2.0,"Y":1.0,"Width":1.0,"Height":1.0,"Contain":false,"Opacity":1.0,"AnimationSpeed":0.0,"OpacityEaseTime":0.0,"HeightEaseTime":0.0,"WidthEaseTime":0.0,"WidthEase":"Linear","HeightEase":"Linear","OpacityEase":"Linear","ConditionType":1,"Conditions":[{"Field":"CurrentTime.Seconds","Value":"2","Operator":"==","Type":"Int32","HotKey":null},{"Field":"CurrentTime.Seconds","Value":"12","Operator":"==","Type":"Int32","HotKey":null},{"Field":"CurrentTime.Seconds","Value":"22","Operator":"==","Type":"Int32","HotKey":null},{"Field":"CurrentTime.Seconds","Value":"32","Operator":"==","Type":"Int32","HotKey":null},{"Field":"CurrentTime.Seconds","Value":"42","Operator":"==","Type":"Int32","HotKey":null},{"Field":"CurrentTime.Seconds","Value":"52","Operator":"==","Type":"Int32","HotKey":null}],"LayerKeybindModels":[],"DynamicProperties":[],"Brush":{"SolidColorBrush":{"@xmlns":"http://schemas.microsoft.com/winfx/2006/xaml/presentation","#text":"#FF8000FF"}}},"EventProperties":null,"Children":[]},{"LayerType":{"$type":"Artemis.Profiles.Layers.Types.Keyboard.KeyboardType, Artemis"},"LayerCondition":{"$type":"Artemis.Profiles.Layers.Conditions.DataModelCondition, Artemis"},"LayerAnimation":{"$type":"Artemis.Profiles.Layers.Animations.NoneAnimation, Artemis"},"Name":"3","Order":3,"Enabled":true,"RenderAllowed":true,"Expanded":false,"IsEvent":false,"Properties":{"$type":"Artemis.Profiles.Layers.Types.Keyboard.KeyboardPropertiesModel, Artemis","GifFile":null,"X":3.0,"Y":1.0,"Width":1.0,"Height":1.0,"Contain":false,"Opacity":1.0,"AnimationSpeed":0.0,"OpacityEaseTime":0.0,"HeightEaseTime":0.0,"WidthEaseTime":0.0,"WidthEase":"Linear","HeightEase":"Linear","OpacityEase":"Linear","ConditionType":1,"Conditions":[{"Field":"CurrentTime.Seconds","Value":"3","Operator":"==","Type":"Int32","HotKey":null},{"Field":"CurrentTime.Seconds","Value":"13","Operator":"==","Type":"Int32","HotKey":null},{"Field":"CurrentTime.Seconds","Value":"23","Operator":"==","Type":"Int32","HotKey":null},{"Field":"CurrentTime.Seconds","Value":"33","Operator":"==","Type":"Int32","HotKey":null},{"Field":"CurrentTime.Seconds","Value":"43","Operator":"==","Type":"Int32","HotKey":null},{"Field":"CurrentTime.Seconds","Value":"53","Operator":"==","Type":"Int32","HotKey":null}],"LayerKeybindModels":[],"DynamicProperties":[],"Brush":{"SolidColorBrush":{"@xmlns":"http://schemas.microsoft.com/winfx/2006/xaml/presentation","#text":"#FF8000FF"}}},"EventProperties":null,"Children":[]},{"LayerType":{"$type":"Artemis.Profiles.Layers.Types.Keyboard.KeyboardType, Artemis"},"LayerCondition":{"$type":"Artemis.Profiles.Layers.Conditions.DataModelCondition, Artemis"},"LayerAnimation":{"$type":"Artemis.Profiles.Layers.Animations.NoneAnimation, Artemis"},"Name":"4","Order":4,"Enabled":true,"RenderAllowed":true,"Expanded":true,"IsEvent":false,"Properties":{"$type":"Artemis.Profiles.Layers.Types.Keyboard.KeyboardPropertiesModel, Artemis","GifFile":null,"X":4.0,"Y":1.0,"Width":1.0,"Height":1.0,"Contain":false,"Opacity":1.0,"AnimationSpeed":0.0,"OpacityEaseTime":0.0,"HeightEaseTime":0.0,"WidthEaseTime":0.0,"WidthEase":"Linear","HeightEase":"Linear","OpacityEase":"Linear","ConditionType":1,"Conditions":[{"Field":"CurrentTime.Seconds","Value":"4","Operator":"==","Type":"Int32","HotKey":null},{"Field":"CurrentTime.Seconds","Value":"14","Operator":"==","Type":"Int32","HotKey":null},{"Field":"CurrentTime.Seconds","Value":"24","Operator":"==","Type":"Int32","HotKey":null},{"Field":"CurrentTime.Seconds","Value":"34","Operator":"==","Type":"Int32","HotKey":null},{"Field":"CurrentTime.Seconds","Value":"44","Operator":"==","Type":"Int32","HotKey":null},{"Field":"CurrentTime.Seconds","Value":"54","Operator":"==","Type":"Int32","HotKey":null}],"LayerKeybindModels":[],"DynamicProperties":[],"Brush":{"SolidColorBrush":{"@xmlns":"http://schemas.microsoft.com/winfx/2006/xaml/presentation","#text":"#FF8000FF"}}},"EventProperties":null,"Children":[]},{"LayerType":{"$type":"Artemis.Profiles.Layers.Types.Keyboard.KeyboardType, Artemis"},"LayerCondition":{"$type":"Artemis.Profiles.Layers.Conditions.DataModelCondition, Artemis"},"LayerAnimation":{"$type":"Artemis.Profiles.Layers.Animations.NoneAnimation, Artemis"},"Name":"5","Order":5,"Enabled":true,"RenderAllowed":true,"Expanded":true,"IsEvent":false,"Properties":{"$type":"Artemis.Profiles.Layers.Types.Keyboard.KeyboardPropertiesModel, Artemis","GifFile":null,"X":5.0,"Y":1.0,"Width":1.0,"Height":1.0,"Contain":false,"Opacity":1.0,"AnimationSpeed":0.0,"OpacityEaseTime":0.0,"HeightEaseTime":0.0,"WidthEaseTime":0.0,"WidthEase":"Linear","HeightEase":"Linear","OpacityEase":"Linear","ConditionType":1,"Conditions":[{"Field":"CurrentTime.Seconds","Value":"5","Operator":"==","Type":"Int32","HotKey":null},{"Field":"CurrentTime.Seconds","Value":"15","Operator":"==","Type":"Int32","HotKey":null},{"Field":"CurrentTime.Seconds","Value":"25","Operator":"==","Type":"Int32","HotKey":null},{"Field":"CurrentTime.Seconds","Value":"35","Operator":"==","Type":"Int32","HotKey":null},{"Field":"CurrentTime.Seconds","Value":"45","Operator":"==","Type":"Int32","HotKey":null},{"Field":"CurrentTime.Seconds","Value":"55","Operator":"==","Type":"Int32","HotKey":null}],"LayerKeybindModels":[],"DynamicProperties":[],"Brush":{"SolidColorBrush":{"@xmlns":"http://schemas.microsoft.com/winfx/2006/xaml/presentation","#text":"#FF8000FF"}}},"EventProperties":null,"Children":[]},{"LayerType":{"$type":"Artemis.Profiles.Layers.Types.Keyboard.KeyboardType, Artemis"},"LayerCondition":{"$type":"Artemis.Profiles.Layers.Conditions.DataModelCondition, Artemis"},"LayerAnimation":{"$type":"Artemis.Profiles.Layers.Animations.NoneAnimation, Artemis"},"Name":"6","Order":6,"Enabled":true,"RenderAllowed":true,"Expanded":false,"IsEvent":false,"Properties":{"$type":"Artemis.Profiles.Layers.Types.Keyboard.KeyboardPropertiesModel, Artemis","GifFile":null,"X":6.0,"Y":1.0,"Width":1.0,"Height":1.0,"Contain":false,"Opacity":1.0,"AnimationSpeed":0.0,"OpacityEaseTime":0.0,"HeightEaseTime":0.0,"WidthEaseTime":0.0,"WidthEase":"Linear","HeightEase":"Linear","OpacityEase":"Linear","ConditionType":1,"Conditions":[{"Field":"CurrentTime.Seconds","Value":"6","Operator":"==","Type":"Int32","HotKey":null},{"Field":"CurrentTime.Seconds","Value":"16","Operator":"==","Type":"Int32","HotKey":null},{"Field":"CurrentTime.Seconds","Value":"26","Operator":"==","Type":"Int32","HotKey":null},{"Field":"CurrentTime.Seconds","Value":"36","Operator":"==","Type":"Int32","HotKey":null},{"Field":"CurrentTime.Seconds","Value":"46","Operator":"==","Type":"Int32","HotKey":null},{"Field":"CurrentTime.Seconds","Value":"56","Operator":"==","Type":"Int32","HotKey":null}],"LayerKeybindModels":[],"DynamicProperties":[],"Brush":{"SolidColorBrush":{"@xmlns":"http://schemas.microsoft.com/winfx/2006/xaml/presentation","#text":"#FF8000FF"}}},"EventProperties":null,"Children":[]},{"LayerType":{"$type":"Artemis.Profiles.Layers.Types.Keyboard.KeyboardType, Artemis"},"LayerCondition":{"$type":"Artemis.Profiles.Layers.Conditions.DataModelCondition, Artemis"},"LayerAnimation":{"$type":"Artemis.Profiles.Layers.Animations.NoneAnimation, Artemis"},"Name":"7","Order":7,"Enabled":true,"RenderAllowed":true,"Expanded":true,"IsEvent":false,"Properties":{"$type":"Artemis.Profiles.Layers.Types.Keyboard.KeyboardPropertiesModel, Artemis","GifFile":null,"X":7.0,"Y":1.0,"Width":1.0,"Height":1.0,"Contain":false,"Opacity":1.0,"AnimationSpeed":0.0,"OpacityEaseTime":0.0,"HeightEaseTime":0.0,"WidthEaseTime":0.0,"WidthEase":"Linear","HeightEase":"Linear","OpacityEase":"Linear","ConditionType":1,"Conditions":[{"Field":"CurrentTime.Seconds","Value":"7","Operator":"==","Type":"Int32","HotKey":null},{"Field":"CurrentTime.Seconds","Value":"17","Operator":"==","Type":"Int32","HotKey":null},{"Field":"CurrentTime.Seconds","Value":"27","Operator":"==","Type":"Int32","HotKey":null},{"Field":"CurrentTime.Seconds","Value":"37","Operator":"==","Type":"Int32","HotKey":null},{"Field":"CurrentTime.Seconds","Value":"47","Operator":"==","Type":"Int32","HotKey":null},{"Field":"CurrentTime.Seconds","Value":"57","Operator":"==","Type":"Int32","HotKey":null}],"LayerKeybindModels":[],"DynamicProperties":[],"Brush":{"SolidColorBrush":{"@xmlns":"http://schemas.microsoft.com/winfx/2006/xaml/presentation","#text":"#FF8000FF"}}},"EventProperties":null,"Children":[]},{"LayerType":{"$type":"Artemis.Profiles.Layers.Types.Keyboard.KeyboardType, Artemis"},"LayerCondition":{"$type":"Artemis.Profiles.Layers.Conditions.DataModelCondition, Artemis"},"LayerAnimation":{"$type":"Artemis.Profiles.Layers.Animations.NoneAnimation, Artemis"},"Name":"8","Order":8,"Enabled":true,"RenderAllowed":true,"Expanded":false,"IsEvent":false,"Properties":{"$type":"Artemis.Profiles.Layers.Types.Keyboard.KeyboardPropertiesModel, Artemis","GifFile":null,"X":8.0,"Y":1.0,"Width":1.0,"Height":1.0,"Contain":false,"Opacity":1.0,"AnimationSpeed":0.0,"OpacityEaseTime":0.0,"HeightEaseTime":0.0,"WidthEaseTime":0.0,"WidthEase":"Linear","HeightEase":"Linear","OpacityEase":"Linear","ConditionType":1,"Conditions":[{"Field":"CurrentTime.Seconds","Value":"8","Operator":"==","Type":"Int32","HotKey":null},{"Field":"CurrentTime.Seconds","Value":"18","Operator":"==","Type":"Int32","HotKey":null},{"Field":"CurrentTime.Seconds","Value":"28","Operator":"==","Type":"Int32","HotKey":null},{"Field":"CurrentTime.Seconds","Value":"38","Operator":"==","Type":"Int32","HotKey":null},{"Field":"CurrentTime.Seconds","Value":"48","Operator":"==","Type":"Int32","HotKey":null},{"Field":"CurrentTime.Seconds","Value":"58","Operator":"==","Type":"Int32","HotKey":null}],"LayerKeybindModels":[],"DynamicProperties":[],"Brush":{"SolidColorBrush":{"@xmlns":"http://schemas.microsoft.com/winfx/2006/xaml/presentation","#text":"#FF8000FF"}}},"EventProperties":null,"Children":[]},{"LayerType":{"$type":"Artemis.Profiles.Layers.Types.Keyboard.KeyboardType, Artemis"},"LayerCondition":{"$type":"Artemis.Profiles.Layers.Conditions.DataModelCondition, Artemis"},"LayerAnimation":{"$type":"Artemis.Profiles.Layers.Animations.NoneAnimation, Artemis"},"Name":"9","Order":9,"Enabled":true,"RenderAllowed":true,"Expanded":true,"IsEvent":false,"Properties":{"$type":"Artemis.Profiles.Layers.Types.Keyboard.KeyboardPropertiesModel, Artemis","GifFile":null,"X":9.0,"Y":1.0,"Width":1.0,"Height":1.0,"Contain":false,"Opacity":1.0,"AnimationSpeed":0.0,"OpacityEaseTime":0.0,"HeightEaseTime":0.0,"WidthEaseTime":0.0,"WidthEase":"Linear","HeightEase":"Linear","OpacityEase":"Linear","ConditionType":1,"Conditions":[{"Field":"CurrentTime.Seconds","Value":"9","Operator":"==","Type":"Int32","HotKey":null},{"Field":"CurrentTime.Seconds","Value":"19","Operator":"==","Type":"Int32","HotKey":null},{"Field":"CurrentTime.Seconds","Value":"29","Operator":"==","Type":"Int32","HotKey":null},{"Field":"CurrentTime.Seconds","Value":"39","Operator":"==","Type":"Int32","HotKey":null},{"Field":"CurrentTime.Seconds","Value":"49","Operator":"==","Type":"Int32","HotKey":null},{"Field":"CurrentTime.Seconds","Value":"59","Operator":"==","Type":"Int32","HotKey":null}],"LayerKeybindModels":[],"DynamicProperties":[],"Brush":{"SolidColorBrush":{"@xmlns":"http://schemas.microsoft.com/winfx/2006/xaml/presentation","#text":"#FF8000FF"}}},"EventProperties":null,"Children":[]},{"LayerType":{"$type":"Artemis.Profiles.Layers.Types.Keyboard.KeyboardType, Artemis"},"LayerCondition":{"$type":"Artemis.Profiles.Layers.Conditions.DataModelCondition, Artemis"},"LayerAnimation":{"$type":"Artemis.Profiles.Layers.Animations.NoneAnimation, Artemis"},"Name":"Keys","Order":10,"Enabled":true,"RenderAllowed":true,"Expanded":true,"IsEvent":false,"Properties":{"$type":"Artemis.Profiles.Layers.Types.Keyboard.KeyboardPropertiesModel, Artemis","GifFile":null,"X":0.0,"Y":0.0,"Width":21.0,"Height":6.0,"Contain":false,"Opacity":1.0,"AnimationSpeed":0.0,"OpacityEaseTime":0.0,"HeightEaseTime":0.0,"WidthEaseTime":0.0,"WidthEase":"Linear","HeightEase":"Linear","OpacityEase":"Linear","ConditionType":0,"Conditions":[],"LayerKeybindModels":[],"DynamicProperties":[],"Brush":{"SolidColorBrush":{"@xmlns":"http://schemas.microsoft.com/winfx/2006/xaml/presentation","#text":"#FF4AFF00"}}},"EventProperties":null,"Children":[]}],"Name":"Timer","IsDefault":false,"KeyboardSlug":"logitech-g810","GameName":"GeneralProfile","Width":21,"Height":6,"LuaScript":"----------------------------------------------------------------------------------\n-------------------------------- Artemis LUA file --------------------------------\n----------------------------------------------------------------------------------\n\n-- This is a default script to be executed by Artemis.\n-- You do not need to use this if you don't want to script. The default profiles\n-- should provide you with a lot of functionality out of the box.\n-- However, if you want to change the way profiles work, this is the ideal way \n-- go about it.\n\n-- For docs and examples, see wiki: https://github.com/SpoinkyNL/Artemis/wiki/LUA\n\n-- Note: You are editing a temporary file. Whenever you save this file the \n-- changes are applied to the profile and the script is restarted.\n\n-- This event is raised after every profile update, before drawing.\nfunction updateHandler(profile, eventArgs)\n\t-- Don't do anything when previewing (this means the editor is open)\n\tif eventArgs.Preview then \n\t\treturn \n\tend\n\n\t-- In this example we only want to update once per frame when the keyboard is \n\t-- updated. If you don't do this the updateHandler will trigger on every\n\t-- device's update.\n    if eventArgs.DeviceType != \"keyboard\" then\n        return\n    end\n\t\n\t-- Custom update code here\nend\n\n-- This event is raised after every profile draw, after updating.\nfunction drawHandler(profile, eventArgs)\n\t-- Don't do anything when previewing (this means the editor is open)\n\tif eventArgs.Preview then \n\t\treturn \n\tend\n\n\t-- In this example we only want to draw to the keyboard. Each device has it's\n\t-- own drawing event\n    if eventArgs.DeviceType != \"keyboard\" then\n        return\n    end\n\t\n\t-- Custom draw code here\nend\n\n\n-- Register the default events, you can rename/remove these if you so desire.\n-- These events are raised every 40 ms (25 times a second).\nEvents.DeviceUpdating.add(updateHandler);\nEvents.DeviceDrawing.add(drawHandler);","LuaStorage":"{}"}